AUTHORS.txt
LICENSE.txt
MANIFEST.in
README.txt
setup.py
src/consume/__init__.py
src/consume/consume.py
src/consume/examples/consume_batch_input_example.csv
src/consume/input_data/EmissionsFactorDatabase.xml
src/consume/input_data/FCCS_loadings.xml
src/consume/tests/test_consume.py
src/python_consume.egg-info/PKG-INFO
src/python_consume.egg-info/SOURCES.txt
src/python_consume.egg-info/dependency_links.txt
src/python_consume.egg-info/requires.txt
src/python_consume.egg-info/top_level.txt