Metadata-Version: 1.0
Name: python-consume
Version: 0.1.1
Summary: Python port of Consume, a software program developed by the USFS that calculates consumption and emissions from wildland fires
Home-page: http://pypi.python.org/pypi/python-consume
Author: Michael Billmire
Author-email: mgbillmi@mtu.edu
License: BSD
Keywords: kml
Platform: UNKNOWN
Classifier: Programming Language :: Python
Classifier: License :: OSI Approved :: BSD License
Classifier: Operating System :: OS Independent
Classifier: Development Status :: 3 - Alpha
Classifier: Intended Audience :: Science/Research
Classifier: Intended Audience :: Developers
Classifier: Topic :: Scientific/Engineering :: Physics
Classifier: Topic :: Software Development :: Libraries :: Python Modules
